Metadata-Version: 2.1
Name: serial-motor-control
Version: 0.1.1
Summary: Motion control used old Api for STM32 firmware
Home-page: https://github.com/Adam-Software/Serial-motor-control
Author: vertigra
Author-email: a@nesterof.com
License: MIT
Platform: UNKNOWN
Classifier: Development Status :: 3 - Alpha
Classifier: License :: OSI Approved :: MIT License
Classifier: Operating System :: POSIX :: Linux
Classifier: Programming Language :: Python :: 3.7
Classifier: Programming Language :: Python :: 3.8
Classifier: Programming Language :: Python :: 3.9
License-File: LICENSE
